emdpy/__init__.py
emdpy/emd.py
emdpy/metrics.py
emdpy/utils.py
emdpy/visualize.py
emdpy/eqs/lineqs_direct.py
emdpy/eqs/lineqs_itera.py
emdpy/insert_value/cubic_spline.py
emdpy/insert_value/lagrange.py
emdpy_z-0.0.3.dist-info/LICENSE
emdpy_z-0.0.3.dist-info/METADATA
emdpy_z-0.0.3.dist-info/WHEEL
emdpy_z-0.0.3.dist-info/top_level.txt
emdpy_z-0.0.3.dist-info/RECORD
